opentakserver/__init__.py
opentakserver/app.py
opentakserver/babel.cfg
opentakserver/blueprints/__init__.py
opentakserver/blueprints/cli.py
opentakserver/blueprints/marti_api/__init__.py
opentakserver/blueprints/marti_api/certificate_enrollment_api.py
opentakserver/blueprints/marti_api/citrap_api.py
opentakserver/blueprints/marti_api/contacts_marti_api.py
opentakserver/blueprints/marti_api/cot_marti_api.py
opentakserver/blueprints/marti_api/data_package_marti_api.py
opentakserver/blueprints/marti_api/device_profile_marti_api.py
opentakserver/blueprints/marti_api/group_marti_api.py
opentakserver/blueprints/marti_api/icons/damaged.png
opentakserver/blueprints/marti_api/icons/team_blue.png
opentakserver/blueprints/marti_api/icons/team_cyan.png
opentakserver/blueprints/marti_api/icons/team_darkblue.png
opentakserver/blueprints/marti_api/icons/team_darkgreen.png
opentakserver/blueprints/marti_api/icons/team_green.png
opentakserver/blueprints/marti_api/icons/team_magenta.png
opentakserver/blueprints/marti_api/icons/team_maroon.png
opentakserver/blueprints/marti_api/icons/team_orange.png
opentakserver/blueprints/marti_api/icons/team_purple.png
opentakserver/blueprints/marti_api/icons/team_red.png
opentakserver/blueprints/marti_api/icons/team_teal.png
opentakserver/blueprints/marti_api/icons/team_white.png
opentakserver/blueprints/marti_api/icons/team_yellow.png
opentakserver/blueprints/marti_api/marti_api.py
opentakserver/blueprints/marti_api/mission_marti_api.py
opentakserver/blueprints/marti_api/video_marti_api.py
opentakserver/blueprints/ots_api/__init__.py
opentakserver/blueprints/ots_api/api.py
opentakserver/blueprints/ots_api/casevac_api.py
opentakserver/blueprints/ots_api/data_package_api.py
opentakserver/blueprints/ots_api/device_profile_api.py
opentakserver/blueprints/ots_api/eud_stats_api.py
opentakserver/blueprints/ots_api/group_api.py
opentakserver/blueprints/ots_api/language_api.py
opentakserver/blueprints/ots_api/ldap_api.py
opentakserver-1.7.4.dist-info/entry_points.txt
opentakserver-1.7.4.dist-info/LICENSE
opentakserver-1.7.4.dist-info/METADATA
opentakserver-1.7.4.dist-info/WHEEL
opentakserver-1.7.4.dist-info/RECORD
