Metadata-Version: 2.1
Name: OpenTAKServer
Version: 1.7.4
Summary: A server for ATAK, WinTAK, and iTAK
Home-page: https://github.com/brian7704/OpenTAKServer
License: GPL-3.0-or-later
Author: OpenTAKServer
Author-email: opentakserver@gmail.com
Requires-Python: >=3.10,<3.15
Classifier: License :: OSI Approved :: GNU General Public License v3 or later (GPLv3+)
Classifier: Programming Language :: Python :: 3
Classifier: Programming Language :: Python :: 3.10
Classifier: Programming Language :: Python :: 3.11
Classifier: Programming Language :: Python :: 3.12
Classifier: Programming Language :: Python :: 3.13
Requires-Dist: Flask-Security-Too[common,mfa] (==5.7.1)
Requires-Dist: PyJWT (==2.10.0)
Requires-Dist: PyYAML (==6.0.3)
Requires-Dist: adsbxcot (==6.0.4)
Requires-Dist: aiscot (==7.0.10)
Requires-Dist: androguard (==4.1.3)
Requires-Dist: beautifulsoup4 (==4.14.2)
Requires-Dist: colorlog (==6.10.1)
Requires-Dist: datetime (==5.5)
Requires-Dist: dulwich (==0.24.1)
Requires-Dist: eventlet (==0.40.3)
Requires-Dist: flask (==3.1.2)
Requires-Dist: flask-apscheduler (==1.13.1)
Requires-Dist: flask-babel (==4.0.0)
Requires-Dist: flask-cors (==6.0.1)
Requires-Dist: flask-ldap3-login (==1.0.2)
Requires-Dist: flask-mailman (==1.1.1)
Requires-Dist: flask-migrate (==4.1.0)
Requires-Dist: flask-socketio (==5.5.1)
Requires-Dist: flask-sqlalchemy (==3.1.1)
Requires-Dist: gevent (==25.5.1)
Requires-Dist: httpx[http2] (==0.28.1)
Requires-Dist: kombu (==5.6.0)
Requires-Dist: lastversion
Requires-Dist: lxml (==6.0.2)
Requires-Dist: meshtastic (==2.7.5)
Requires-Dist: pika (==1.3.2)
Requires-Dist: poetry (==2.2.1)
Requires-Dist: poetry-dynamic-versioning[plugin] (==1.9.1)
Requires-Dist: protobuf (==6.33.1)
Requires-Dist: psutil (==7.1.3)
Requires-Dist: psycopg (==3.2.12)
Requires-Dist: pyOpenSSL (==25.3.0)
Requires-Dist: pyfiglet (==1.0.2)
Requires-Dist: pygc (==2.0.0)
Requires-Dist: pyotp (==2.9.0)
Requires-Dist: pytak (==7.0.2)
Requires-Dist: pytest (==8.3.3)
Requires-Dist: pytest-cov (==6.0.0)
Requires-Dist: python-ffmpeg (==2.0.12)
Requires-Dist: python-socketio[asyncio-client,client,websocket-client] (==5.14.3)
Requires-Dist: semver (==3.0.4)
Requires-Dist: simplekml (==1.3.6)
Requires-Dist: sqlalchemy (==2.0.44)
Requires-Dist: sqlalchemy-utils (==0.42.0)
Requires-Dist: tldextract (==5.3.0)
Requires-Dist: unishox2-py3 (==1.0.0)
Requires-Dist: yt-dlp
Requires-Dist: zope-event (==5.1.1)
Requires-Dist: zope-interface (==8.1.1)
Project-URL: Documentation, https://docs.opentakserver.io
Project-URL: Repository, https://github.com/brian7704/OpenTAKServer
